{
    "basic": {
        "description": "This course provides students from any discipline with an integrated interdisciplinary learning experience. The course is taught by instructors from at least two different departments and/or colleges. Topics vary. May be repeated to a maximum of twelve semester hours.", 
        "number": "4934", 
        "subject": "HUM", 
        "title": "Interdisciplinary Topics"
    }, 
    "extra": {
        "career": "Undergraduate", 
        "course_components": {
            "Class Lecture": "Required", 
            "Discussion": "Optional"
        }, 
        "grading_basis": "Graded", 
        "units": "3.00"
    }
}