{
    "basic": {
        "description": "This course introduces graduate students and upper-level undergraduates to the diversity of musical cultures from the African continent. Students explore various case studies from the continent and develop tools to interpret their musical value and contextual meaning. A background interest in music, anthropology, performance studies, or African studies is recommended.", 
        "number": "5536", 
        "subject": "MUH", 
        "title": "African Soundscapes"
    }, 
    "extra": {
        "career": "Graduate", 
        "course_components": {
            "Class Lecture": "Required"
        }, 
        "grading_basis": "Graded", 
        "typically_offered": "Fall, Spring", 
        "units": "3.00"
    }
}