{
    "basic": {
        "description": "This course prepares pre-service teachers to teach beginning reading, targeting the needs of a wide range of learners, including those of varying abilities and from diverse cultures. The content addresses research-based strategies, materials, technology, assessment, classroom management, and collaboration with other professionals and parents.", 
        "number": "4310", 
        "subject": "RED", 
        "title": "Early Literacy Learning"
    }, 
    "extra": {
        "career": "Undergraduate", 
        "course_components": {
            "Class Lecture": "Required"
        }, 
        "enrollment_requirement": "Prerequisites: EDF 1005 and EDF 2085.", 
        "grading_basis": "Graded", 
        "typically_offered": "Fall, Spring", 
        "units": "3.00"
    }
}