{
    "_unique": "0003-DSS (9062)", 
    "basic": {
        "class_num": "9062", 
        "course": "6980", 
        "season": "Spring", 
        "solus_id": "0003", 
        "status": "Open", 
        "subject": "PSY", 
        "type": "DSS", 
        "year": "2016"
    }, 
    "classes": [
        {
            "day_of_week": null, 
            "end_time": null, 
            "instructors": [
                "Neil Charness"
            ], 
            "location": "TBA", 
            "start_time": null, 
            "term_end": "2016-04-29", 
            "term_start": "2016-01-06"
        }
    ]
}