{
    "_unique": "0006-DIS (4408)", 
    "basic": {
        "class_num": "4408", 
        "course": "4905", 
        "season": "Spring", 
        "solus_id": "0006", 
        "status": "Closed", 
        "subject": "HUN", 
        "type": "DIS", 
        "year": "2016"
    }, 
    "classes": [
        {
            "day_of_week": null, 
            "end_time": null, 
            "instructors": [
                "Michael Ormsbee"
            ], 
            "location": "TBA", 
            "start_time": null, 
            "term_end": "2016-04-29", 
            "term_start": "2016-01-06"
        }
    ]
}