{
    "_unique": "0007-LAB (494)", 
    "basic": {
        "class_num": "494", 
        "course": "4901", 
        "season": "Spring", 
        "solus_id": "0007", 
        "status": "Closed", 
        "subject": "BMS", 
        "type": "LAB", 
        "year": "2016"
    }, 
    "classes": [
        {
            "day_of_week": null, 
            "end_time": null, 
            "instructors": [
                "Gregg Stanwood"
            ], 
            "location": "TBA", 
            "start_time": null, 
            "term_end": "2016-04-29", 
            "term_start": "2016-01-06"
        }
    ]
}