{
    "_unique": "0005-PRF (7005)", 
    "basic": {
        "class_num": "7005", 
        "course": "1313", 
        "season": "Spring", 
        "solus_id": "0005", 
        "status": "Closed", 
        "subject": "MVB", 
        "type": "PRF", 
        "year": "2016"
    }, 
    "classes": [
        {
            "day_of_week": null, 
            "end_time": null, 
            "instructors": [
                "Christopher Brown"
            ], 
            "location": "TBA", 
            "start_time": null, 
            "term_end": "2016-04-29", 
            "term_start": "2016-01-06"
        }
    ]
}