{
    "_unique": "0002-LAB (8266)", 
    "basic": {
        "class_num": "8266", 
        "course": "4888L", 
        "season": "Spring", 
        "solus_id": "0002", 
        "status": "Closed", 
        "subject": "NUR", 
        "type": "LAB", 
        "year": "2016"
    }, 
    "classes": [
        {
            "day_of_week": null, 
            "end_time": null, 
            "instructors": [
                "So Hyun Park"
            ], 
            "location": "TBA", 
            "start_time": null, 
            "term_end": "2016-02-26", 
            "term_start": "2016-01-06"
        }
    ]
}