{
    "_unique": "0001-LAB (1290)", 
    "basic": {
        "class_num": "1290", 
        "course": "3508L", 
        "season": "Spring", 
        "solus_id": "0001", 
        "status": "Closed", 
        "subject": "CGN", 
        "type": "LAB", 
        "year": "2016"
    }, 
    "classes": [
        {
            "day_of_week": 5, 
            "end_time": "13:30:00", 
            "instructors": [
                "Raphael Kampmann"
            ], 
            "location": "CE1 0111", 
            "start_time": "11:00:00", 
            "term_end": "2016-04-29", 
            "term_start": "2016-01-06"
        }
    ]
}