{
    "_unique": "0001-PRF (7326)", 
    "basic": {
        "class_num": "7326", 
        "course": "5250", 
        "season": "Spring", 
        "solus_id": "0001", 
        "status": "Closed", 
        "subject": "MVO", 
        "type": "PRF", 
        "year": "2016"
    }, 
    "classes": [
        {
            "day_of_week": null, 
            "end_time": null, 
            "instructors": [
                "Iain Quinn"
            ], 
            "location": "TBA", 
            "start_time": null, 
            "term_end": "2016-04-29", 
            "term_start": "2016-01-06"
        }
    ]
}