{
    "_unique": "0001-MED (462)", 
    "basic": {
        "class_num": "462", 
        "course": "6940", 
        "season": "Spring", 
        "solus_id": "0001", 
        "status": "Open", 
        "subject": "BMS", 
        "type": "MED", 
        "year": "2016"
    }, 
    "classes": [
        {
            "day_of_week": null, 
            "end_time": null, 
            "instructors": [
                "Luckey Dunn"
            ], 
            "location": "TBA", 
            "start_time": null, 
            "term_end": "2016-05-06", 
            "term_start": "2016-01-04"
        }
    ]
}