{
    "_unique": "0004-LEC (6281)", 
    "basic": {
        "class_num": "6281", 
        "course": "5125", 
        "season": "Spring", 
        "solus_id": "0004", 
        "status": "Closed", 
        "subject": "MUN", 
        "type": "LEC", 
        "year": "2016"
    }, 
    "classes": [
        {
            "day_of_week": 2, 
            "end_time": "21:45:00", 
            "instructors": [], 
            "location": "HMU N0114", 
            "start_time": "19:30:00", 
            "term_end": "2016-04-29", 
            "term_start": "2016-01-06"
        }
    ]
}