{
    "_unique": "0006-PRF (7876)", 
    "basic": {
        "class_num": "7876", 
        "course": "4241", 
        "season": "Spring", 
        "solus_id": "0006", 
        "status": "Closed", 
        "subject": "MVV", 
        "type": "PRF", 
        "year": "2016"
    }, 
    "classes": [
        {
            "day_of_week": null, 
            "end_time": null, 
            "instructors": [
                "Rahim Mandal-Munoz"
            ], 
            "location": "TBA", 
            "start_time": null, 
            "term_end": "2016-04-29", 
            "term_start": "2016-01-06"
        }
    ]
}